gigax/__init__.py
gigax/parse.py
gigax/prompt.py
gigax/scene.py
gigax/step.py
gigax/serve/__init__.py
gigax/serve/app.py
tests/__init__.py
tests/conftest.py
tests/test_parse.py
tests/test_prompt.py
tests/test_step.py
gigax-0.1.dist-info/METADATA
gigax-0.1.dist-info/WHEEL
gigax-0.1.dist-info/top_level.txt
gigax-0.1.dist-info/RECORD
